{"cameraMode":{"drawMode":0,"name":"Shaded","section":"Shading Mode"},"sceneLighting":true,"audioPlay":false,"sceneViewState":{"m_AlwaysRefresh":false,"showFog":true,"showSkybox":true,"showFlares":true,"showImageEffects":true,"showParticleSystems":true,"showVisualEffectGraphs":true,"m_FxEnabled":true},"in2DMode":false,"pivot":{"x":-4.414175987243652,"y":0.9012972116470337,"z":4.414175987243652},"rotation":{"x":-0.4607146084308624,"y":-0.09499328583478928,"z":0.049673572182655337,"w":-0.8810542225837708},"size":2.8732047080993654,"orthographic":false}